{
  "values": [
    {
      "csName": "P",
      "csOrder": 1,
      "price": 31.0,
      "dayX": -20,
      "demand": 3.22
    },
    {
      "csName": "A",
      "csOrder": 2,
      "price": 31.0,
      "dayX": -20,
      "demand": 3.22
    },
    {
      "csName": "N",
      "csOrder": 3,
      "price": 39.0,
      "dayX": -20,
      "demand": 3.09
    },
    {
      "csName": "G",
      "csOrder": 4,
      "price": 47.0,
      "dayX": -20,
      "demand": 3.0
    },
    {
      "csName": "T",
      "csOrder": 5,
      "price": 57.0,
      "dayX": -20,
      "demand": 2.88
    },
    {
      "csName": "R",
      "csOrder": 6,
      "price": 71.0,
      "dayX": -20,
      "demand": 2.76
    },
    {
      "csName": "X",
      "csOrder": 7,
      "price": 84.0,
      "dayX": -20,
      "demand": 2.4628
    },
    {
      "csName": "L",
      "csOrder": 8,
      "price": 98.0,
      "dayX": -20,
      "demand": 1.984
    },
    {
      "csName": "K",
      "csOrder": 9,
      "price": 112.0,
      "dayX": -20,
      "demand": 1.5246000000000002
    },
    {
      "csName": "V",
      "csOrder": 10,
      "price": 129.0,
      "dayX": -20,
      "demand": 1.4058
    },
    {
      "csName": "Q",
      "csOrder": 11,
      "price": 148.0,
      "dayX": -20,
      "demand": 1.287
    },
    {
      "csName": "H",
      "csOrder": 12,
      "price": 166.0,
      "dayX": -20,
      "demand": 1.155
    },
    {
      "csName": "M",
      "csOrder": 13,
      "price": 186.0,
      "dayX": -20,
      "demand": 1.0098
    },
    {
      "csName": "I",
      "csOrder": 14,
      "price": 208.0,
      "dayX": -20,
      "demand": 0.8514
    },
    {
      "csName": "F",
      "csOrder": 15,
      "price": 231.0,
      "dayX": -20,
      "demand": 0.6996000000000001
    },
    {
      "csName": "B",
      "csOrder": 16,
      "price": 254.0,
      "dayX": -20,
      "demand": 0.528
    },
    {
      "csName": "D",
      "csOrder": 17,
      "price": 278.0,
      "dayX": -20,
      "demand": 0.36300000000000004
    },
    {
      "csName": "S",
      "csOrder": 18,
      "price": 301.0,
      "dayX": -20,
      "demand": 0.1584
    },
    {
      "csName": "J",
      "csOrder": 19,
      "price": 330.0,
      "dayX": -20,
      "demand": 0.0
    },
    {
      "csName": "Z",
      "csOrder": 20,
      "price": 360.0,
      "dayX": -20,
      "demand": 0.0
    },
    {
      "csName": "Y",
      "csOrder": 21,
      "price": 390.0,
      "dayX": -20,
      "demand": 0.0
    },
    {
      "csName": "P",
      "csOrder": 1,
      "price": 31.0,
      "dayX": -19,
      "demand": 3.11
    },
    {
      "csName": "A",
      "csOrder": 2,
      "price": 31.0,
      "dayX": -19,
      "demand": 3.11
    },
    {
      "csName": "N",
      "csOrder": 3,
      "price": 39.0,
      "dayX": -19,
      "demand": 3.01
    },
    {
      "csName": "G",
      "csOrder": 4,
      "price": 47.0,
      "dayX": -19,
      "demand": 2.94
    },
    {
      "csName": "T",
      "csOrder": 5,
      "price": 57.0,
      "dayX": -19,
      "demand": 2.84
    },
    {
      "csName": "R",
      "csOrder": 6,
      "price": 71.0,
      "dayX": -19,
      "demand": 2.75
    },
    {
      "csName": "X",
      "csOrder": 7,
      "price": 84.0,
      "dayX": -19,
      "demand": 2.508
    },
    {
      "csName": "L",
      "csOrder": 8,
      "price": 98.0,
      "dayX": -19,
      "demand": 2.1252
    },
    {
      "csName": "K",
      "csOrder": 9,
      "price": 112.0,
      "dayX": -19,
      "demand": 1.752
    },
    {
      "csName": "V",
      "csOrder": 10,
      "price": 129.0,
      "dayX": -19,
      "demand": 1.6497999999999997
    },
    {
      "csName": "Q",
      "csOrder": 11,
      "price": 148.0,
      "dayX": -19,
      "demand": 1.5402999999999998
    },
    {
      "csName": "H",
      "csOrder": 12,
      "price": 166.0,
      "dayX": -19,
      "demand": 1.4235
    },
    {
      "csName": "M",
      "csOrder": 13,
      "price": 186.0,
      "dayX": -19,
      "demand": 1.2993999999999999
    },
    {
      "csName": "I",
      "csOrder": 14,
      "price": 208.0,
      "dayX": -19,
      "demand": 1.1607
    },
    {
      "csName": "F",
      "csOrder": 15,
      "price": 231.0,
      "dayX": -19,
      "demand": 1.0292999999999999
    },
    {
      "csName": "B",
      "csOrder": 16,
      "price": 254.0,
      "dayX": -19,
      "demand": 0.8833
    },
    {
      "csName": "D",
      "csOrder": 17,
      "price": 278.0,
      "dayX": -19,
      "demand": 0.73
    },
    {
      "csName": "S",
      "csOrder": 18,
      "price": 301.0,
      "dayX": -19,
      "demand": 0.5548
    },
    {
      "csName": "J",
      "csOrder": 19,
      "price": 330.0,
      "dayX": -19,
      "demand": 0.3723
    },
    {
      "csName": "Z",
      "csOrder": 20,
      "price": 360.0,
      "dayX": -19,
      "demand": 0.1679
    },
    {
      "csName": "Y",
      "csOrder": 21,
      "price": 390.0,
      "dayX": -19,
      "demand": 0.0
    },
    {
      "csName": "P",
      "csOrder": 1,
      "price": 31.0,
      "dayX": -18,
      "demand": 3.02
    },
    {
      "csName": "A",
      "csOrder": 2,
      "price": 31.0,
      "dayX": -18,
      "demand": 3.02
    },
    {
      "csName": "N",
      "csOrder": 3,
      "price": 39.0,
      "dayX": -18,
      "demand": 2.93
    },
    {
      "csName": "G",
      "csOrder": 4,
      "price": 47.0,
      "dayX": -18,
      "demand": 2.87
    },
    {
      "csName": "T",
      "csOrder": 5,
      "price": 57.0,
      "dayX": -18,
      "demand": 2.8
    },
    {
      "csName": "R",
      "csOrder": 6,
      "price": 71.0,
      "dayX": -18,
      "demand": 2.72
    },
    {
      "csName": "X",
      "csOrder": 7,
      "price": 84.0,
      "dayX": -18,
      "demand": 2.5511
    },
    {
      "csName": "L",
      "csOrder": 8,
      "price": 98.0,
      "dayX": -18,
      "demand": 2.2352
    },
    {
      "csName": "K",
      "csOrder": 9,
      "price": 112.0,
      "dayX": -18,
      "demand": 1.9440000000000002
    },
    {
      "csName": "V",
      "csOrder": 10,
      "price": 129.0,
      "dayX": -18,
      "demand": 1.8559999999999999
    },
    {
      "csName": "Q",
      "csOrder": 11,
      "price": 148.0,
      "dayX": -18,
      "demand": 1.752
    },
    {
      "csName": "H",
      "csOrder": 12,
      "price": 166.0,
      "dayX": -18,
      "demand": 1.656
    },
    {
      "csName": "M",
      "csOrder": 13,
      "price": 186.0,
      "dayX": -18,
      "demand": 1.544
    },
    {
      "csName": "I",
      "csOrder": 14,
      "price": 208.0,
      "dayX": -18,
      "demand": 1.4160000000000001
    },
    {
      "csName": "F",
      "csOrder": 15,
      "price": 231.0,
      "dayX": -18,
      "demand": 1.2960000000000003
    },
    {
      "csName": "B",
      "csOrder": 16,
      "price": 254.0,
      "dayX": -18,
      "demand": 1.168
    },
    {
      "csName": "D",
      "csOrder": 17,
      "price": 278.0,
      "dayX": -18,
      "demand": 1.032
    },
    {
      "csName": "S",
      "csOrder": 18,
      "price": 301.0,
      "dayX": -18,
      "demand": 0.8720000000000001
    },
    {
      "csName": "J",
      "csOrder": 19,
      "price": 330.0,
      "dayX": -18,
      "demand": 0.7120000000000001
    },
    {
      "csName": "Z",
      "csOrder": 20,
      "price": 360.0,
      "dayX": -18,
      "demand": 0.536
    },
    {
      "csName": "Y",
      "csOrder": 21,
      "price": 390.0,
      "dayX": -18,
      "demand": 0.36000000000000004
    },
    {
      "csName": "P",
      "csOrder": 1,
      "price": 31.0,
      "dayX": -17,
      "demand": 2.73
    },
    {
      "csName": "A",
      "csOrder": 2,
      "price": 31.0,
      "dayX": -17,
      "demand": 2.73
    },
    {
      "csName": "N",
      "csOrder": 3,
      "price": 39.0,
      "dayX": -17,
      "demand": 2.66
    },
    {
      "csName": "G",
      "csOrder": 4,
      "price": 47.0,
      "dayX": -17,
      "demand": 2.61
    },
    {
      "csName": "T",
      "csOrder": 5,
      "price": 57.0,
      "dayX": -17,
      "demand": 2.54
    },
    {
      "csName": "R",
      "csOrder": 6,
      "price": 71.0,
      "dayX": -17,
      "demand": 2.48
    },
    {
      "csName": "X",
      "csOrder": 7,
      "price": 84.0,
      "dayX": -17,
      "demand": 2.3618
    },
    {
      "csName": "L",
      "csOrder": 8,
      "price": 98.0,
      "dayX": -17,
      "demand": 2.1436
    },
    {
      "csName": "K",
      "csOrder": 9,
      "price": 112.0,
      "dayX": -17,
      "demand": 1.9178
    },
    {
      "csName": "V",
      "csOrder": 10,
      "price": 129.0,
      "dayX": -17,
      "demand": 1.8404
    },
    {
      "csName": "Q",
      "csOrder": 11,
      "price": 148.0,
      "dayX": -17,
      "demand": 1.7457999999999998
    },
    {
      "csName": "H",
      "csOrder": 12,
      "price": 166.0,
      "dayX": -17,
      "demand": 1.6512
    },
    {
      "csName": "M",
      "csOrder": 13,
      "price": 186.0,
      "dayX": -17,
      "demand": 1.5566
    },
    {
      "csName": "I",
      "csOrder": 14,
      "price": 208.0,
      "dayX": -17,
      "demand": 1.4447999999999999
    },
    {
      "csName": "F",
      "csOrder": 15,
      "price": 231.0,
      "dayX": -17,
      "demand": 1.333
    },
    {
      "csName": "B",
      "csOrder": 16,
      "price": 254.0,
      "dayX": -17,
      "demand": 1.2126
    },
    {
      "csName": "D",
      "csOrder": 17,
      "price": 278.0,
      "dayX": -17,
      "demand": 1.0922
    },
    {
      "csName": "S",
      "csOrder": 18,
      "price": 301.0,
      "dayX": -17,
      "demand": 0.9460000000000001
    },
    {
      "csName": "J",
      "csOrder": 19,
      "price": 330.0,
      "dayX": -17,
      "demand": 0.7912
    },
    {
      "csName": "Z",
      "csOrder": 20,
      "price": 360.0,
      "dayX": -17,
      "demand": 0.6278
    },
    {
      "csName": "Y",
      "csOrder": 21,
      "price": 390.0,
      "dayX": -17,
      "demand": 0.47300000000000003
    },
    {
      "csName": "P",
      "csOrder": 1,
      "price": 31.0,
      "dayX": -16,
      "demand": 2.37
    },
    {
      "csName": "A",
      "csOrder": 2,
      "price": 31.0,
      "dayX": -16,
      "demand": 2.37
    },
    {
      "csName": "N",
      "csOrder": 3,
      "price": 39.0,
      "dayX": -16,
      "demand": 2.26
    },
    {
      "csName": "G",
      "csOrder": 4,
      "price": 47.0,
      "dayX": -16,
      "demand": 2.18
    },
    {
      "csName": "T",
      "csOrder": 5,
      "price": 57.0,
      "dayX": -16,
      "demand": 2.08
    },
    {
      "csName": "R",
      "csOrder": 6,
      "price": 71.0,
      "dayX": -16,
      "demand": 1.98
    },
    {
      "csName": "X",
      "csOrder": 7,
      "price": 84.0,
      "dayX": -16,
      "demand": 1.8513000000000002
    },
    {
      "csName": "L",
      "csOrder": 8,
      "price": 98.0,
      "dayX": -16,
      "demand": 1.68
    },
    {
      "csName": "K",
      "csOrder": 9,
      "price": 112.0,
      "dayX": -16,
      "demand": 1.5066000000000002
    },
    {
      "csName": "V",
      "csOrder": 10,
      "price": 129.0,
      "dayX": -16,
      "demand": 1.3671
    },
    {
      "csName": "Q",
      "csOrder": 11,
      "price": 148.0,
      "dayX": -16,
      "demand": 1.2183000000000002
    },
    {
      "csName": "H",
      "csOrder": 12,
      "price": 166.0,
      "dayX": -16,
      "demand": 1.0695
    },
    {
      "csName": "M",
      "csOrder": 13,
      "price": 186.0,
      "dayX": -16,
      "demand": 0.9021
    },
    {
      "csName": "I",
      "csOrder": 14,
      "price": 208.0,
      "dayX": -16,
      "demand": 0.7161000000000001
    },
    {
      "csName": "F",
      "csOrder": 15,
      "price": 231.0,
      "dayX": -16,
      "demand": 0.5394
    },
    {
      "csName": "B",
      "csOrder": 16,
      "price": 254.0,
      "dayX": -16,
      "demand": 0.3441
    },
    {
      "csName": "D",
      "csOrder": 17,
      "price": 278.0,
      "dayX": -16,
      "demand": 0.14880000000000002
    },
    {
      "csName": "S",
      "csOrder": 18,
      "price": 301.0,
      "dayX": -16,
      "demand": 0.0
    },
    {
      "csName": "J",
      "csOrder": 19,
      "price": 330.0,
      "dayX": -16,
      "demand": 0.0
    },
    {
      "csName": "Z",
      "csOrder": 20,
      "price": 360.0,
      "dayX": -16,
      "demand": 0.0
    },
    {
      "csName": "Y",
      "csOrder": 21,
      "price": 390.0,
      "dayX": -16,
      "demand": 0.0
    },
    {
      "csName": "P",
      "csOrder": 1,
      "price": 31.0,
      "dayX": -15,
      "demand": 2.43
    },
    {
      "csName": "A",
      "csOrder": 2,
      "price": 31.0,
      "dayX": -15,
      "demand": 2.43
    },
    {
      "csName": "N",
      "csOrder": 3,
      "price": 39.0,
      "dayX": -15,
      "demand": 2.3
    },
    {
      "csName": "G",
      "csOrder": 4,
      "price": 47.0,
      "dayX": -15,
      "demand": 2.21
    },
    {
      "csName": "T",
      "csOrder": 5,
      "price": 57.0,
      "dayX": -15,
      "demand": 2.09
    },
    {
      "csName": "R",
      "csOrder": 6,
      "price": 71.0,
      "dayX": -15,
      "demand": 1.96
    },
    {
      "csName": "X",
      "csOrder": 7,
      "price": 84.0,
      "dayX": -15,
      "demand": 1.83
    },
    {
      "csName": "L",
      "csOrder": 8,
      "price": 98.0,
      "dayX": -15,
      "demand": 1.69
    },
    {
      "csName": "K",
      "csOrder": 9,
      "price": 112.0,
      "dayX": -15,
      "demand": 1.52
    },
    {
      "csName": "V",
      "csOrder": 10,
      "price": 129.0,
      "dayX": -15,
      "demand": 1.34
    },
    {
      "csName": "Q",
      "csOrder": 11,
      "price": 148.0,
      "dayX": -15,
      "demand": 1.16
    },
    {
      "csName": "H",
      "csOrder": 12,
      "price": 166.0,
      "dayX": -15,
      "demand": 0.96
    },
    {
      "csName": "M",
      "csOrder": 13,
      "price": 186.0,
      "dayX": -15,
      "demand": 0.75
    },
    {
      "csName": "I",
      "csOrder": 14,
      "price": 208.0,
      "dayX": -15,
      "demand": 0.5
    },
    {
      "csName": "F",
      "csOrder": 15,
      "price": 231.0,
      "dayX": -15,
      "demand": 0.27
    },
    {
      "csName": "B",
      "csOrder": 16,
      "price": 254.0,
      "dayX": -15,
      "demand": 0.02
    },
    {
      "csName": "D",
      "csOrder": 17,
      "price": 278.0,
      "dayX": -15,
      "demand": 0.0
    },
    {
      "csName": "S",
      "csOrder": 18,
      "price": 301.0,
      "dayX": -15,
      "demand": 0.0
    },
    {
      "csName": "J",
      "csOrder": 19,
      "price": 330.0,
      "dayX": -15,
      "demand": 0.0
    },
    {
      "csName": "Z",
      "csOrder": 20,
      "price": 360.0,
      "dayX": -15,
      "demand": 0.0
    },
    {
      "csName": "Y",
      "csOrder": 21,
      "price": 390.0,
      "dayX": -15,
      "demand": 0.0
    },
    {
      "csName": "P",
      "csOrder": 1,
      "price": 31.0,
      "dayX": -14,
      "demand": 3.48
    },
    {
      "csName": "A",
      "csOrder": 2,
      "price": 31.0,
      "dayX": -14,
      "demand": 3.48
    },
    {
      "csName": "N",
      "csOrder": 3,
      "price": 39.0,
      "dayX": -14,
      "demand": 3.36
    },
    {
      "csName": "G",
      "csOrder": 4,
      "price": 47.0,
      "dayX": -14,
      "demand": 3.28
    },
    {
      "csName": "T",
      "csOrder": 5,
      "price": 57.0,
      "dayX": -14,
      "demand": 3.18
    },
    {
      "csName": "R",
      "csOrder": 6,
      "price": 71.0,
      "dayX": -14,
      "demand": 3.07
    },
    {
      "csName": "X",
      "csOrder": 7,
      "price": 84.0,
      "dayX": -14,
      "demand": 2.95
    },
    {
      "csName": "L",
      "csOrder": 8,
      "price": 98.0,
      "dayX": -14,
      "demand": 2.82
    },
    {
      "csName": "K",
      "csOrder": 9,
      "price": 112.0,
      "dayX": -14,
      "demand": 2.68
    },
    {
      "csName": "V",
      "csOrder": 10,
      "price": 129.0,
      "dayX": -14,
      "demand": 2.52
    },
    {
      "csName": "Q",
      "csOrder": 11,
      "price": 148.0,
      "dayX": -14,
      "demand": 2.35
    },
    {
      "csName": "H",
      "csOrder": 12,
      "price": 166.0,
      "dayX": -14,
      "demand": 2.18
    },
    {
      "csName": "M",
      "csOrder": 13,
      "price": 186.0,
      "dayX": -14,
      "demand": 1.99
    },
    {
      "csName": "I",
      "csOrder": 14,
      "price": 208.0,
      "dayX": -14,
      "demand": 1.78
    },
    {
      "csName": "F",
      "csOrder": 15,
      "price": 231.0,
      "dayX": -14,
      "demand": 1.57
    },
    {
      "csName": "B",
      "csOrder": 16,
      "price": 254.0,
      "dayX": -14,
      "demand": 1.35
    },
    {
      "csName": "D",
      "csOrder": 17,
      "price": 278.0,
      "dayX": -14,
      "demand": 1.12
    },
    {
      "csName": "S",
      "csOrder": 18,
      "price": 301.0,
      "dayX": -14,
      "demand": 0.85
    },
    {
      "csName": "J",
      "csOrder": 19,
      "price": 330.0,
      "dayX": -14,
      "demand": 0.57
    },
    {
      "csName": "Z",
      "csOrder": 20,
      "price": 360.0,
      "dayX": -14,
      "demand": 0.26
    },
    {
      "csName": "Y",
      "csOrder": 21,
      "price": 390.0,
      "dayX": -14,
      "demand": 0.0
    },
    {
      "csName": "P",
      "csOrder": 1,
      "price": 31.0,
      "dayX": -13,
      "demand": 3.96
    },
    {
      "csName": "A",
      "csOrder": 2,
      "price": 31.0,
      "dayX": -13,
      "demand": 3.96
    },
    {
      "csName": "N",
      "csOrder": 3,
      "price": 39.0,
      "dayX": -13,
      "demand": 3.82
    },
    {
      "csName": "G",
      "csOrder": 4,
      "price": 47.0,
      "dayX": -13,
      "demand": 3.73
    },
    {
      "csName": "T",
      "csOrder": 5,
      "price": 57.0,
      "dayX": -13,
      "demand": 3.61
    },
    {
      "csName": "R",
      "csOrder": 6,
      "price": 71.0,
      "dayX": -13,
      "demand": 3.48
    },
    {
      "csName": "X",
      "csOrder": 7,
      "price": 84.0,
      "dayX": -13,
      "demand": 3.34
    },
    {
      "csName": "L",
      "csOrder": 8,
      "price": 98.0,
      "dayX": -13,
      "demand": 3.2
    },
    {
      "csName": "K",
      "csOrder": 9,
      "price": 112.0,
      "dayX": -13,
      "demand": 3.03
    },
    {
      "csName": "V",
      "csOrder": 10,
      "price": 129.0,
      "dayX": -13,
      "demand": 2.84
    },
    {
      "csName": "Q",
      "csOrder": 11,
      "price": 148.0,
      "dayX": -13,
      "demand": 2.65
    },
    {
      "csName": "H",
      "csOrder": 12,
      "price": 166.0,
      "dayX": -13,
      "demand": 2.44
    },
    {
      "csName": "M",
      "csOrder": 13,
      "price": 186.0,
      "dayX": -13,
      "demand": 2.23
    },
    {
      "csName": "I",
      "csOrder": 14,
      "price": 208.0,
      "dayX": -13,
      "demand": 1.98
    },
    {
      "csName": "F",
      "csOrder": 15,
      "price": 231.0,
      "dayX": -13,
      "demand": 1.74
    },
    {
      "csName": "B",
      "csOrder": 16,
      "price": 254.0,
      "dayX": -13,
      "demand": 1.48
    },
    {
      "csName": "D",
      "csOrder": 17,
      "price": 278.0,
      "dayX": -13,
      "demand": 1.21
    },
    {
      "csName": "S",
      "csOrder": 18,
      "price": 301.0,
      "dayX": -13,
      "demand": 0.89
    },
    {
      "csName": "J",
      "csOrder": 19,
      "price": 330.0,
      "dayX": -13,
      "demand": 0.56
    },
    {
      "csName": "Z",
      "csOrder": 20,
      "price": 360.0,
      "dayX": -13,
      "demand": 0.21
    },
    {
      "csName": "Y",
      "csOrder": 21,
      "price": 390.0,
      "dayX": -13,
      "demand": 0.0
    },
    {
      "csName": "P",
      "csOrder": 1,
      "price": 31.0,
      "dayX": -12,
      "demand": 4.06
    },
    {
      "csName": "A",
      "csOrder": 2,
      "price": 31.0,
      "dayX": -12,
      "demand": 4.06
    },
    {
      "csName": "N",
      "csOrder": 3,
      "price": 39.0,
      "dayX": -12,
      "demand": 3.9
    },
    {
      "csName": "G",
      "csOrder": 4,
      "price": 47.0,
      "dayX": -12,
      "demand": 3.8
    },
    {
      "csName": "T",
      "csOrder": 5,
      "price": 57.0,
      "dayX": -12,
      "demand": 3.65
    },
    {
      "csName": "R",
      "csOrder": 6,
      "price": 71.0,
      "dayX": -12,
      "demand": 3.51
    },
    {
      "csName": "X",
      "csOrder": 7,
      "price": 84.0,
      "dayX": -12,
      "demand": 3.35
    },
    {
      "csName": "L",
      "csOrder": 8,
      "price": 98.0,
      "dayX": -12,
      "demand": 3.18
    },
    {
      "csName": "K",
      "csOrder": 9,
      "price": 112.0,
      "dayX": -12,
      "demand": 2.98
    },
    {
      "csName": "V",
      "csOrder": 10,
      "price": 129.0,
      "dayX": -12,
      "demand": 2.77
    },
    {
      "csName": "Q",
      "csOrder": 11,
      "price": 148.0,
      "dayX": -12,
      "demand": 2.55
    },
    {
      "csName": "H",
      "csOrder": 12,
      "price": 166.0,
      "dayX": -12,
      "demand": 2.31
    },
    {
      "csName": "M",
      "csOrder": 13,
      "price": 186.0,
      "dayX": -12,
      "demand": 2.06
    },
    {
      "csName": "I",
      "csOrder": 14,
      "price": 208.0,
      "dayX": -12,
      "demand": 1.77
    },
    {
      "csName": "F",
      "csOrder": 15,
      "price": 231.0,
      "dayX": -12,
      "demand": 1.49
    },
    {
      "csName": "B",
      "csOrder": 16,
      "price": 254.0,
      "dayX": -12,
      "demand": 1.19
    },
    {
      "csName": "D",
      "csOrder": 17,
      "price": 278.0,
      "dayX": -12,
      "demand": 0.89
    },
    {
      "csName": "S",
      "csOrder": 18,
      "price": 301.0,
      "dayX": -12,
      "demand": 0.52
    },
    {
      "csName": "J",
      "csOrder": 19,
      "price": 330.0,
      "dayX": -12,
      "demand": 0.14
    },
    {
      "csName": "Z",
      "csOrder": 20,
      "price": 360.0,
      "dayX": -12,
      "demand": 0.0
    },
    {
      "csName": "Y",
      "csOrder": 21,
      "price": 390.0,
      "dayX": -12,
      "demand": 0.0
    },
    {
      "csName": "P",
      "csOrder": 1,
      "price": 31.0,
      "dayX": -11,
      "demand": 4.21
    },
    {
      "csName": "A",
      "csOrder": 2,
      "price": 31.0,
      "dayX": -11,
      "demand": 4.21
    },
    {
      "csName": "N",
      "csOrder": 3,
      "price": 39.0,
      "dayX": -11,
      "demand": 4.08
    },
    {
      "csName": "G",
      "csOrder": 4,
      "price": 47.0,
      "dayX": -11,
      "demand": 3.99
    },
    {
      "csName": "T",
      "csOrder": 5,
      "price": 57.0,
      "dayX": -11,
      "demand": 3.87
    },
    {
      "csName": "R",
      "csOrder": 6,
      "price": 71.0,
      "dayX": -11,
      "demand": 3.75
    },
    {
      "csName": "X",
      "csOrder": 7,
      "price": 84.0,
      "dayX": -11,
      "demand": 3.62
    },
    {
      "csName": "L",
      "csOrder": 8,
      "price": 98.0,
      "dayX": -11,
      "demand": 3.47
    },
    {
      "csName": "K",
      "csOrder": 9,
      "price": 112.0,
      "dayX": -11,
      "demand": 3.31
    },
    {
      "csName": "V",
      "csOrder": 10,
      "price": 129.0,
      "dayX": -11,
      "demand": 3.13
    },
    {
      "csName": "Q",
      "csOrder": 11,
      "price": 148.0,
      "dayX": -11,
      "demand": 2.95
    },
    {
      "csName": "H",
      "csOrder": 12,
      "price": 166.0,
      "dayX": -11,
      "demand": 2.75
    },
    {
      "csName": "M",
      "csOrder": 13,
      "price": 186.0,
      "dayX": -11,
      "demand": 2.54
    },
    {
      "csName": "I",
      "csOrder": 14,
      "price": 208.0,
      "dayX": -11,
      "demand": 2.3
    },
    {
      "csName": "F",
      "csOrder": 15,
      "price": 231.0,
      "dayX": -11,
      "demand": 2.07
    },
    {
      "csName": "B",
      "csOrder": 16,
      "price": 254.0,
      "dayX": -11,
      "demand": 1.82
    },
    {
      "csName": "D",
      "csOrder": 17,
      "price": 278.0,
      "dayX": -11,
      "demand": 1.56
    },
    {
      "csName": "S",
      "csOrder": 18,
      "price": 301.0,
      "dayX": -11,
      "demand": 1.26
    },
    {
      "csName": "J",
      "csOrder": 19,
      "price": 330.0,
      "dayX": -11,
      "demand": 0.94
    },
    {
      "csName": "Z",
      "csOrder": 20,
      "price": 360.0,
      "dayX": -11,
      "demand": 0.6
    },
    {
      "csName": "Y",
      "csOrder": 21,
      "price": 390.0,
      "dayX": -11,
      "demand": 0.27
    },
    {
      "csName": "P",
      "csOrder": 1,
      "price": 31.0,
      "dayX": -10,
      "demand": 3.69
    },
    {
      "csName": "A",
      "csOrder": 2,
      "price": 31.0,
      "dayX": -10,
      "demand": 3.69
    },
    {
      "csName": "N",
      "csOrder": 3,
      "price": 39.0,
      "dayX": -10,
      "demand": 3.55
    },
    {
      "csName": "G",
      "csOrder": 4,
      "price": 47.0,
      "dayX": -10,
      "demand": 3.46
    },
    {
      "csName": "T",
      "csOrder": 5,
      "price": 57.0,
      "dayX": -10,
      "demand": 3.33
    },
    {
      "csName": "R",
      "csOrder": 6,
      "price": 71.0,
      "dayX": -10,
      "demand": 3.2
    },
    {
      "csName": "X",
      "csOrder": 7,
      "price": 84.0,
      "dayX": -10,
      "demand": 3.05
    },
    {
      "csName": "L",
      "csOrder": 8,
      "price": 98.0,
      "dayX": -10,
      "demand": 2.9
    },
    {
      "csName": "K",
      "csOrder": 9,
      "price": 112.0,
      "dayX": -10,
      "demand": 2.72
    },
    {
      "csName": "V",
      "csOrder": 10,
      "price": 129.0,
      "dayX": -10,
      "demand": 2.53
    },
    {
      "csName": "Q",
      "csOrder": 11,
      "price": 148.0,
      "dayX": -10,
      "demand": 2.33
    },
    {
      "csName": "H",
      "csOrder": 12,
      "price": 166.0,
      "dayX": -10,
      "demand": 2.12
    },
    {
      "csName": "M",
      "csOrder": 13,
      "price": 186.0,
      "dayX": -10,
      "demand": 1.89
    },
    {
      "csName": "I",
      "csOrder": 14,
      "price": 208.0,
      "dayX": -10,
      "demand": 1.63
    },
    {
      "csName": "F",
      "csOrder": 15,
      "price": 231.0,
      "dayX": -10,
      "demand": 1.38
    },
    {
      "csName": "B",
      "csOrder": 16,
      "price": 254.0,
      "dayX": -10,
      "demand": 1.11
    },
    {
      "csName": "D",
      "csOrder": 17,
      "price": 278.0,
      "dayX": -10,
      "demand": 0.83
    },
    {
      "csName": "S",
      "csOrder": 18,
      "price": 301.0,
      "dayX": -10,
      "demand": 0.5
    },
    {
      "csName": "J",
      "csOrder": 19,
      "price": 330.0,
      "dayX": -10,
      "demand": 0.16
    },
    {
      "csName": "Z",
      "csOrder": 20,
      "price": 360.0,
      "dayX": -10,
      "demand": 0.0
    },
    {
      "csName": "Y",
      "csOrder": 21,
      "price": 390.0,
      "dayX": -10,
      "demand": 0.0
    },
    {
      "csName": "P",
      "csOrder": 1,
      "price": 31.0,
      "dayX": -9,
      "demand": 2.75
    },
    {
      "csName": "A",
      "csOrder": 2,
      "price": 31.0,
      "dayX": -9,
      "demand": 2.75
    },
    {
      "csName": "N",
      "csOrder": 3,
      "price": 39.0,
      "dayX": -9,
      "demand": 2.64
    },
    {
      "csName": "G",
      "csOrder": 4,
      "price": 47.0,
      "dayX": -9,
      "demand": 2.56
    },
    {
      "csName": "T",
      "csOrder": 5,
      "price": 57.0,
      "dayX": -9,
      "demand": 2.45
    },
    {
      "csName": "R",
      "csOrder": 6,
      "price": 71.0,
      "dayX": -9,
      "demand": 2.34
    },
    {
      "csName": "X",
      "csOrder": 7,
      "price": 84.0,
      "dayX": -9,
      "demand": 2.23
    },
    {
      "csName": "L",
      "csOrder": 8,
      "price": 98.0,
      "dayX": -9,
      "demand": 2.1
    },
    {
      "csName": "K",
      "csOrder": 9,
      "price": 112.0,
      "dayX": -9,
      "demand": 1.96
    },
    {
      "csName": "V",
      "csOrder": 10,
      "price": 129.0,
      "dayX": -9,
      "demand": 1.8
    },
    {
      "csName": "Q",
      "csOrder": 11,
      "price": 148.0,
      "dayX": -9,
      "demand": 1.64
    },
    {
      "csName": "H",
      "csOrder": 12,
      "price": 166.0,
      "dayX": -9,
      "demand": 1.46
    },
    {
      "csName": "M",
      "csOrder": 13,
      "price": 186.0,
      "dayX": -9,
      "demand": 1.28
    },
    {
      "csName": "I",
      "csOrder": 14,
      "price": 208.0,
      "dayX": -9,
      "demand": 1.06
    },
    {
      "csName": "F",
      "csOrder": 15,
      "price": 231.0,
      "dayX": -9,
      "demand": 0.86
    },
    {
      "csName": "B",
      "csOrder": 16,
      "price": 254.0,
      "dayX": -9,
      "demand": 0.64
    },
    {
      "csName": "D",
      "csOrder": 17,
      "price": 278.0,
      "dayX": -9,
      "demand": 0.41
    },
    {
      "csName": "S",
      "csOrder": 18,
      "price": 301.0,
      "dayX": -9,
      "demand": 0.14
    },
    {
      "csName": "J",
      "csOrder": 19,
      "price": 330.0,
      "dayX": -9,
      "demand": 0.0
    },
    {
      "csName": "Z",
      "csOrder": 20,
      "price": 360.0,
      "dayX": -9,
      "demand": 0.0
    },
    {
      "csName": "Y",
      "csOrder": 21,
      "price": 390.0,
      "dayX": -9,
      "demand": 0.0
    },
    {
      "csName": "P",
      "csOrder": 1,
      "price": 31.0,
      "dayX": -8,
      "demand": 3.04
    },
    {
      "csName": "A",
      "csOrder": 2,
      "price": 31.0,
      "dayX": -8,
      "demand": 3.04
    },
    {
      "csName": "N",
      "csOrder": 3,
      "price": 39.0,
      "dayX": -8,
      "demand": 2.91
    },
    {
      "csName": "G",
      "csOrder": 4,
      "price": 47.0,
      "dayX": -8,
      "demand": 2.82
    },
    {
      "csName": "T",
      "csOrder": 5,
      "price": 57.0,
      "dayX": -8,
      "demand": 2.71
    },
    {
      "csName": "R",
      "csOrder": 6,
      "price": 71.0,
      "dayX": -8,
      "demand": 2.59
    },
    {
      "csName": "X",
      "csOrder": 7,
      "price": 84.0,
      "dayX": -8,
      "demand": 2.46
    },
    {
      "csName": "L",
      "csOrder": 8,
      "price": 98.0,
      "dayX": -8,
      "demand": 2.32
    },
    {
      "csName": "K",
      "csOrder": 9,
      "price": 112.0,
      "dayX": -8,
      "demand": 2.16
    },
    {
      "csName": "V",
      "csOrder": 10,
      "price": 129.0,
      "dayX": -8,
      "demand": 1.99
    },
    {
      "csName": "Q",
      "csOrder": 11,
      "price": 148.0,
      "dayX": -8,
      "demand": 1.81
    },
    {
      "csName": "H",
      "csOrder": 12,
      "price": 166.0,
      "dayX": -8,
      "demand": 1.62
    },
    {
      "csName": "M",
      "csOrder": 13,
      "price": 186.0,
      "dayX": -8,
      "demand": 1.42
    },
    {
      "csName": "I",
      "csOrder": 14,
      "price": 208.0,
      "dayX": -8,
      "demand": 1.18
    },
    {
      "csName": "F",
      "csOrder": 15,
      "price": 231.0,
      "dayX": -8,
      "demand": 0.96
    },
    {
      "csName": "B",
      "csOrder": 16,
      "price": 254.0,
      "dayX": -8,
      "demand": 0.72
    },
    {
      "csName": "D",
      "csOrder": 17,
      "price": 278.0,
      "dayX": -8,
      "demand": 0.47
    },
    {
      "csName": "S",
      "csOrder": 18,
      "price": 301.0,
      "dayX": -8,
      "demand": 0.17
    },
    {
      "csName": "J",
      "csOrder": 19,
      "price": 330.0,
      "dayX": -8,
      "demand": 0.0
    },
    {
      "csName": "Z",
      "csOrder": 20,
      "price": 360.0,
      "dayX": -8,
      "demand": 0.0
    },
    {
      "csName": "Y",
      "csOrder": 21,
      "price": 390.0,
      "dayX": -8,
      "demand": 0.0
    },
    {
      "csName": "P",
      "csOrder": 1,
      "price": 31.0,
      "dayX": -7,
      "demand": 4.9
    },
    {
      "csName": "A",
      "csOrder": 2,
      "price": 31.0,
      "dayX": -7,
      "demand": 4.9
    },
    {
      "csName": "N",
      "csOrder": 3,
      "price": 39.0,
      "dayX": -7,
      "demand": 4.75
    },
    {
      "csName": "G",
      "csOrder": 4,
      "price": 47.0,
      "dayX": -7,
      "demand": 4.65
    },
    {
      "csName": "T",
      "csOrder": 5,
      "price": 57.0,
      "dayX": -7,
      "demand": 4.51
    },
    {
      "csName": "R",
      "csOrder": 6,
      "price": 71.0,
      "dayX": -7,
      "demand": 4.38
    },
    {
      "csName": "X",
      "csOrder": 7,
      "price": 84.0,
      "dayX": -7,
      "demand": 4.23
    },
    {
      "csName": "L",
      "csOrder": 8,
      "price": 98.0,
      "dayX": -7,
      "demand": 4.07
    },
    {
      "csName": "K",
      "csOrder": 9,
      "price": 112.0,
      "dayX": -7,
      "demand": 3.88
    },
    {
      "csName": "V",
      "csOrder": 10,
      "price": 129.0,
      "dayX": -7,
      "demand": 3.68
    },
    {
      "csName": "Q",
      "csOrder": 11,
      "price": 148.0,
      "dayX": -7,
      "demand": 3.47
    },
    {
      "csName": "H",
      "csOrder": 12,
      "price": 166.0,
      "dayX": -7,
      "demand": 3.25
    },
    {
      "csName": "M",
      "csOrder": 13,
      "price": 186.0,
      "dayX": -7,
      "demand": 3.01
    },
    {
      "csName": "I",
      "csOrder": 14,
      "price": 208.0,
      "dayX": -7,
      "demand": 2.74
    },
    {
      "csName": "F",
      "csOrder": 15,
      "price": 231.0,
      "dayX": -7,
      "demand": 2.48
    },
    {
      "csName": "B",
      "csOrder": 16,
      "price": 254.0,
      "dayX": -7,
      "demand": 2.19
    },
    {
      "csName": "D",
      "csOrder": 17,
      "price": 278.0,
      "dayX": -7,
      "demand": 1.9
    },
    {
      "csName": "S",
      "csOrder": 18,
      "price": 301.0,
      "dayX": -7,
      "demand": 1.56
    },
    {
      "csName": "J",
      "csOrder": 19,
      "price": 330.0,
      "dayX": -7,
      "demand": 1.2
    },
    {
      "csName": "Z",
      "csOrder": 20,
      "price": 360.0,
      "dayX": -7,
      "demand": 0.81
    },
    {
      "csName": "Y",
      "csOrder": 21,
      "price": 390.0,
      "dayX": -7,
      "demand": 0.44
    },
    {
      "csName": "P",
      "csOrder": 1,
      "price": 31.0,
      "dayX": -6,
      "demand": 5.08
    },
    {
      "csName": "A",
      "csOrder": 2,
      "price": 31.0,
      "dayX": -6,
      "demand": 5.08
    },
    {
      "csName": "N",
      "csOrder": 3,
      "price": 39.0,
      "dayX": -6,
      "demand": 4.93
    },
    {
      "csName": "G",
      "csOrder": 4,
      "price": 47.0,
      "dayX": -6,
      "demand": 4.84
    },
    {
      "csName": "T",
      "csOrder": 5,
      "price": 57.0,
      "dayX": -6,
      "demand": 4.7
    },
    {
      "csName": "R",
      "csOrder": 6,
      "price": 71.0,
      "dayX": -6,
      "demand": 4.57
    },
    {
      "csName": "X",
      "csOrder": 7,
      "price": 84.0,
      "dayX": -6,
      "demand": 4.43
    },
    {
      "csName": "L",
      "csOrder": 8,
      "price": 98.0,
      "dayX": -6,
      "demand": 4.27
    },
    {
      "csName": "K",
      "csOrder": 9,
      "price": 112.0,
      "dayX": -6,
      "demand": 4.09
    },
    {
      "csName": "V",
      "csOrder": 10,
      "price": 129.0,
      "dayX": -6,
      "demand": 3.9
    },
    {
      "csName": "Q",
      "csOrder": 11,
      "price": 148.0,
      "dayX": -6,
      "demand": 3.7
    },
    {
      "csName": "H",
      "csOrder": 12,
      "price": 166.0,
      "dayX": -6,
      "demand": 3.48
    },
    {
      "csName": "M",
      "csOrder": 13,
      "price": 186.0,
      "dayX": -6,
      "demand": 3.25
    },
    {
      "csName": "I",
      "csOrder": 14,
      "price": 208.0,
      "dayX": -6,
      "demand": 2.99
    },
    {
      "csName": "F",
      "csOrder": 15,
      "price": 231.0,
      "dayX": -6,
      "demand": 2.73
    },
    {
      "csName": "B",
      "csOrder": 16,
      "price": 254.0,
      "dayX": -6,
      "demand": 2.46
    },
    {
      "csName": "D",
      "csOrder": 17,
      "price": 278.0,
      "dayX": -6,
      "demand": 2.18
    },
    {
      "csName": "S",
      "csOrder": 18,
      "price": 301.0,
      "dayX": -6,
      "demand": 1.85
    },
    {
      "csName": "J",
      "csOrder": 19,
      "price": 330.0,
      "dayX": -6,
      "demand": 1.5
    },
    {
      "csName": "Z",
      "csOrder": 20,
      "price": 360.0,
      "dayX": -6,
      "demand": 1.12
    },
    {
      "csName": "Y",
      "csOrder": 21,
      "price": 390.0,
      "dayX": -6,
      "demand": 0.76
    },
    {
      "csName": "P",
      "csOrder": 1,
      "price": 31.0,
      "dayX": -5,
      "demand": 5.14
    },
    {
      "csName": "A",
      "csOrder": 2,
      "price": 31.0,
      "dayX": -5,
      "demand": 5.14
    },
    {
      "csName": "N",
      "csOrder": 3,
      "price": 39.0,
      "dayX": -5,
      "demand": 4.98
    },
    {
      "csName": "G",
      "csOrder": 4,
      "price": 47.0,
      "dayX": -5,
      "demand": 4.87
    },
    {
      "csName": "T",
      "csOrder": 5,
      "price": 57.0,
      "dayX": -5,
      "demand": 4.72
    },
    {
      "csName": "R",
      "csOrder": 6,
      "price": 71.0,
      "dayX": -5,
      "demand": 4.57
    },
    {
      "csName": "X",
      "csOrder": 7,
      "price": 84.0,
      "dayX": -5,
      "demand": 4.41
    },
    {
      "csName": "L",
      "csOrder": 8,
      "price": 98.0,
      "dayX": -5,
      "demand": 4.23
    },
    {
      "csName": "K",
      "csOrder": 9,
      "price": 112.0,
      "dayX": -5,
      "demand": 4.03
    },
    {
      "csName": "V",
      "csOrder": 10,
      "price": 129.0,
      "dayX": -5,
      "demand": 3.81
    },
    {
      "csName": "Q",
      "csOrder": 11,
      "price": 148.0,
      "dayX": -5,
      "demand": 3.58
    },
    {
      "csName": "H",
      "csOrder": 12,
      "price": 166.0,
      "dayX": -5,
      "demand": 3.33
    },
    {
      "csName": "M",
      "csOrder": 13,
      "price": 186.0,
      "dayX": -5,
      "demand": 3.08
    },
    {
      "csName": "I",
      "csOrder": 14,
      "price": 208.0,
      "dayX": -5,
      "demand": 2.78
    },
    {
      "csName": "F",
      "csOrder": 15,
      "price": 231.0,
      "dayX": -5,
      "demand": 2.49
    },
    {
      "csName": "B",
      "csOrder": 16,
      "price": 254.0,
      "dayX": -5,
      "demand": 2.18
    },
    {
      "csName": "D",
      "csOrder": 17,
      "price": 278.0,
      "dayX": -5,
      "demand": 1.87
    },
    {
      "csName": "S",
      "csOrder": 18,
      "price": 301.0,
      "dayX": -5,
      "demand": 1.49
    },
    {
      "csName": "J",
      "csOrder": 19,
      "price": 330.0,
      "dayX": -5,
      "demand": 1.09
    },
    {
      "csName": "Z",
      "csOrder": 20,
      "price": 360.0,
      "dayX": -5,
      "demand": 0.67
    },
    {
      "csName": "Y",
      "csOrder": 21,
      "price": 390.0,
      "dayX": -5,
      "demand": 0.26
    },
    {
      "csName": "P",
      "csOrder": 1,
      "price": 31.0,
      "dayX": -4,
      "demand": 4.87
    },
    {
      "csName": "A",
      "csOrder": 2,
      "price": 31.0,
      "dayX": -4,
      "demand": 4.87
    },
    {
      "csName": "N",
      "csOrder": 3,
      "price": 39.0,
      "dayX": -4,
      "demand": 4.76
    },
    {
      "csName": "G",
      "csOrder": 4,
      "price": 47.0,
      "dayX": -4,
      "demand": 4.69
    },
    {
      "csName": "T",
      "csOrder": 5,
      "price": 57.0,
      "dayX": -4,
      "demand": 4.6
    },
    {
      "csName": "R",
      "csOrder": 6,
      "price": 71.0,
      "dayX": -4,
      "demand": 4.5
    },
    {
      "csName": "X",
      "csOrder": 7,
      "price": 84.0,
      "dayX": -4,
      "demand": 4.39
    },
    {
      "csName": "L",
      "csOrder": 8,
      "price": 98.0,
      "dayX": -4,
      "demand": 4.28
    },
    {
      "csName": "K",
      "csOrder": 9,
      "price": 112.0,
      "dayX": -4,
      "demand": 4.15
    },
    {
      "csName": "V",
      "csOrder": 10,
      "price": 129.0,
      "dayX": -4,
      "demand": 4.01
    },
    {
      "csName": "Q",
      "csOrder": 11,
      "price": 148.0,
      "dayX": -4,
      "demand": 3.86
    },
    {
      "csName": "H",
      "csOrder": 12,
      "price": 166.0,
      "dayX": -4,
      "demand": 3.7
    },
    {
      "csName": "M",
      "csOrder": 13,
      "price": 186.0,
      "dayX": -4,
      "demand": 3.53
    },
    {
      "csName": "I",
      "csOrder": 14,
      "price": 208.0,
      "dayX": -4,
      "demand": 3.34
    },
    {
      "csName": "F",
      "csOrder": 15,
      "price": 231.0,
      "dayX": -4,
      "demand": 3.15
    },
    {
      "csName": "B",
      "csOrder": 16,
      "price": 254.0,
      "dayX": -4,
      "demand": 2.95
    },
    {
      "csName": "D",
      "csOrder": 17,
      "price": 278.0,
      "dayX": -4,
      "demand": 2.75
    },
    {
      "csName": "S",
      "csOrder": 18,
      "price": 301.0,
      "dayX": -4,
      "demand": 2.5
    },
    {
      "csName": "J",
      "csOrder": 19,
      "price": 330.0,
      "dayX": -4,
      "demand": 2.25
    },
    {
      "csName": "Z",
      "csOrder": 20,
      "price": 360.0,
      "dayX": -4,
      "demand": 1.98
    },
    {
      "csName": "Y",
      "csOrder": 21,
      "price": 390.0,
      "dayX": -4,
      "demand": 1.71
    },
    {
      "csName": "P",
      "csOrder": 1,
      "price": 31.0,
      "dayX": -3,
      "demand": 5.24
    },
    {
      "csName": "A",
      "csOrder": 2,
      "price": 31.0,
      "dayX": -3,
      "demand": 5.24
    },
    {
      "csName": "N",
      "csOrder": 3,
      "price": 39.0,
      "dayX": -3,
      "demand": 5.11
    },
    {
      "csName": "G",
      "csOrder": 4,
      "price": 47.0,
      "dayX": -3,
      "demand": 5.03
    },
    {
      "csName": "T",
      "csOrder": 5,
      "price": 57.0,
      "dayX": -3,
      "demand": 4.91
    },
    {
      "csName": "R",
      "csOrder": 6,
      "price": 71.0,
      "dayX": -3,
      "demand": 4.79
    },
    {
      "csName": "X",
      "csOrder": 7,
      "price": 84.0,
      "dayX": -3,
      "demand": 4.66
    },
    {
      "csName": "L",
      "csOrder": 8,
      "price": 98.0,
      "dayX": -3,
      "demand": 4.52
    },
    {
      "csName": "K",
      "csOrder": 9,
      "price": 112.0,
      "dayX": -3,
      "demand": 4.36
    },
    {
      "csName": "V",
      "csOrder": 10,
      "price": 129.0,
      "dayX": -3,
      "demand": 4.19
    },
    {
      "csName": "Q",
      "csOrder": 11,
      "price": 148.0,
      "dayX": -3,
      "demand": 4.01
    },
    {
      "csName": "H",
      "csOrder": 12,
      "price": 166.0,
      "dayX": -3,
      "demand": 3.81
    },
    {
      "csName": "M",
      "csOrder": 13,
      "price": 186.0,
      "dayX": -3,
      "demand": 3.61
    },
    {
      "csName": "I",
      "csOrder": 14,
      "price": 208.0,
      "dayX": -3,
      "demand": 3.37
    },
    {
      "csName": "F",
      "csOrder": 15,
      "price": 231.0,
      "dayX": -3,
      "demand": 3.15
    },
    {
      "csName": "B",
      "csOrder": 16,
      "price": 254.0,
      "dayX": -3,
      "demand": 2.9
    },
    {
      "csName": "D",
      "csOrder": 17,
      "price": 278.0,
      "dayX": -3,
      "demand": 2.65
    },
    {
      "csName": "S",
      "csOrder": 18,
      "price": 301.0,
      "dayX": -3,
      "demand": 2.35
    },
    {
      "csName": "J",
      "csOrder": 19,
      "price": 330.0,
      "dayX": -3,
      "demand": 2.04
    },
    {
      "csName": "Z",
      "csOrder": 20,
      "price": 360.0,
      "dayX": -3,
      "demand": 1.71
    },
    {
      "csName": "Y",
      "csOrder": 21,
      "price": 390.0,
      "dayX": -3,
      "demand": 1.39
    },
    {
      "csName": "P",
      "csOrder": 1,
      "price": 31.0,
      "dayX": -2,
      "demand": 5.36
    },
    {
      "csName": "A",
      "csOrder": 2,
      "price": 31.0,
      "dayX": -2,
      "demand": 5.36
    },
    {
      "csName": "N",
      "csOrder": 3,
      "price": 39.0,
      "dayX": -2,
      "demand": 5.18
    },
    {
      "csName": "G",
      "csOrder": 4,
      "price": 47.0,
      "dayX": -2,
      "demand": 5.06
    },
    {
      "csName": "T",
      "csOrder": 5,
      "price": 57.0,
      "dayX": -2,
      "demand": 4.89
    },
    {
      "csName": "R",
      "csOrder": 6,
      "price": 71.0,
      "dayX": -2,
      "demand": 4.72
    },
    {
      "csName": "X",
      "csOrder": 7,
      "price": 84.0,
      "dayX": -2,
      "demand": 4.53
    },
    {
      "csName": "L",
      "csOrder": 8,
      "price": 98.0,
      "dayX": -2,
      "demand": 4.33
    },
    {
      "csName": "K",
      "csOrder": 9,
      "price": 112.0,
      "dayX": -2,
      "demand": 4.1
    },
    {
      "csName": "V",
      "csOrder": 10,
      "price": 129.0,
      "dayX": -2,
      "demand": 3.86
    },
    {
      "csName": "Q",
      "csOrder": 11,
      "price": 148.0,
      "dayX": -2,
      "demand": 3.6
    },
    {
      "csName": "H",
      "csOrder": 12,
      "price": 166.0,
      "dayX": -2,
      "demand": 3.32
    },
    {
      "csName": "M",
      "csOrder": 13,
      "price": 186.0,
      "dayX": -2,
      "demand": 3.03
    },
    {
      "csName": "I",
      "csOrder": 14,
      "price": 208.0,
      "dayX": -2,
      "demand": 2.69
    },
    {
      "csName": "F",
      "csOrder": 15,
      "price": 231.0,
      "dayX": -2,
      "demand": 2.37
    },
    {
      "csName": "B",
      "csOrder": 16,
      "price": 254.0,
      "dayX": -2,
      "demand": 2.01
    },
    {
      "csName": "D",
      "csOrder": 17,
      "price": 278.0,
      "dayX": -2,
      "demand": 1.66
    },
    {
      "csName": "S",
      "csOrder": 18,
      "price": 301.0,
      "dayX": -2,
      "demand": 1.23
    },
    {
      "csName": "J",
      "csOrder": 19,
      "price": 330.0,
      "dayX": -2,
      "demand": 0.78
    },
    {
      "csName": "Z",
      "csOrder": 20,
      "price": 360.0,
      "dayX": -2,
      "demand": 0.31
    },
    {
      "csName": "Y",
      "csOrder": 21,
      "price": 390.0,
      "dayX": -2,
      "demand": 0.0
    },
    {
      "csName": "P",
      "csOrder": 1,
      "price": 31.0,
      "dayX": -1,
      "demand": 7.57
    },
    {
      "csName": "A",
      "csOrder": 2,
      "price": 31.0,
      "dayX": -1,
      "demand": 7.57
    },
    {
      "csName": "N",
      "csOrder": 3,
      "price": 39.0,
      "dayX": -1,
      "demand": 7.42
    },
    {
      "csName": "G",
      "csOrder": 4,
      "price": 47.0,
      "dayX": -1,
      "demand": 7.32
    },
    {
      "csName": "T",
      "csOrder": 5,
      "price": 57.0,
      "dayX": -1,
      "demand": 7.18
    },
    {
      "csName": "R",
      "csOrder": 6,
      "price": 71.0,
      "dayX": -1,
      "demand": 7.04
    },
    {
      "csName": "X",
      "csOrder": 7,
      "price": 84.0,
      "dayX": -1,
      "demand": 6.89
    },
    {
      "csName": "L",
      "csOrder": 8,
      "price": 98.0,
      "dayX": -1,
      "demand": 6.72
    },
    {
      "csName": "K",
      "csOrder": 9,
      "price": 112.0,
      "dayX": -1,
      "demand": 6.53
    },
    {
      "csName": "V",
      "csOrder": 10,
      "price": 129.0,
      "dayX": -1,
      "demand": 6.32
    },
    {
      "csName": "Q",
      "csOrder": 11,
      "price": 148.0,
      "dayX": -1,
      "demand": 6.11
    },
    {
      "csName": "H",
      "csOrder": 12,
      "price": 166.0,
      "dayX": -1,
      "demand": 5.88
    },
    {
      "csName": "M",
      "csOrder": 13,
      "price": 186.0,
      "dayX": -1,
      "demand": 5.63
    },
    {
      "csName": "I",
      "csOrder": 14,
      "price": 208.0,
      "dayX": -1,
      "demand": 5.35
    },
    {
      "csName": "F",
      "csOrder": 15,
      "price": 231.0,
      "dayX": -1,
      "demand": 5.09
    },
    {
      "csName": "B",
      "csOrder": 16,
      "price": 254.0,
      "dayX": -1,
      "demand": 4.79
    },
    {
      "csName": "D",
      "csOrder": 17,
      "price": 278.0,
      "dayX": -1,
      "demand": 4.5
    },
    {
      "csName": "S",
      "csOrder": 18,
      "price": 301.0,
      "dayX": -1,
      "demand": 4.14
    },
    {
      "csName": "J",
      "csOrder": 19,
      "price": 330.0,
      "dayX": -1,
      "demand": 3.77
    },
    {
      "csName": "Z",
      "csOrder": 20,
      "price": 360.0,
      "dayX": -1,
      "demand": 3.38
    },
    {
      "csName": "Y",
      "csOrder": 21,
      "price": 390.0,
      "dayX": -1,
      "demand": 2.99
    },
    {
      "csName": "P",
      "csOrder": 1,
      "price": 31.0,
      "dayX": 0,
      "demand": 4.61
    },
    {
      "csName": "A",
      "csOrder": 2,
      "price": 31.0,
      "dayX": 0,
      "demand": 4.61
    },
    {
      "csName": "N",
      "csOrder": 3,
      "price": 39.0,
      "dayX": 0,
      "demand": 4.54
    },
    {
      "csName": "G",
      "csOrder": 4,
      "price": 47.0,
      "dayX": 0,
      "demand": 4.49
    },
    {
      "csName": "T",
      "csOrder": 5,
      "price": 57.0,
      "dayX": 0,
      "demand": 4.43
    },
    {
      "csName": "R",
      "csOrder": 6,
      "price": 71.0,
      "dayX": 0,
      "demand": 4.37
    },
    {
      "csName": "X",
      "csOrder": 7,
      "price": 84.0,
      "dayX": 0,
      "demand": 4.3
    },
    {
      "csName": "L",
      "csOrder": 8,
      "price": 98.0,
      "dayX": 0,
      "demand": 4.23
    },
    {
      "csName": "K",
      "csOrder": 9,
      "price": 112.0,
      "dayX": 0,
      "demand": 4.15
    },
    {
      "csName": "V",
      "csOrder": 10,
      "price": 129.0,
      "dayX": 0,
      "demand": 4.06
    },
    {
      "csName": "Q",
      "csOrder": 11,
      "price": 148.0,
      "dayX": 0,
      "demand": 3.96
    },
    {
      "csName": "H",
      "csOrder": 12,
      "price": 166.0,
      "dayX": 0,
      "demand": 3.86
    },
    {
      "csName": "M",
      "csOrder": 13,
      "price": 186.0,
      "dayX": 0,
      "demand": 3.75
    },
    {
      "csName": "I",
      "csOrder": 14,
      "price": 208.0,
      "dayX": 0,
      "demand": 3.63
    },
    {
      "csName": "F",
      "csOrder": 15,
      "price": 231.0,
      "dayX": 0,
      "demand": 3.51
    },
    {
      "csName": "B",
      "csOrder": 16,
      "price": 254.0,
      "dayX": 0,
      "demand": 3.38
    },
    {
      "csName": "D",
      "csOrder": 17,
      "price": 278.0,
      "dayX": 0,
      "demand": 3.25
    },
    {
      "csName": "S",
      "csOrder": 18,
      "price": 301.0,
      "dayX": 0,
      "demand": 3.09
    },
    {
      "csName": "J",
      "csOrder": 19,
      "price": 330.0,
      "dayX": 0,
      "demand": 2.93
    },
    {
      "csName": "Z",
      "csOrder": 20,
      "price": 360.0,
      "dayX": 0,
      "demand": 2.75
    },
    {
      "csName": "Y",
      "csOrder": 21,
      "price": 390.0,
      "dayX": 0,
      "demand": 2.59
    }
  ]
}